MANIFEST.in
requirements.txt
setup.py
examples/example_command.py
examples/example_web.py
examples/filecache_config.conf
examples/memcache_config.conf
wurfl_cloud/__init__.py
wurfl_cloud/utils.py
wurfl_cloud.egg-info/PKG-INFO
wurfl_cloud.egg-info/SOURCES.txt
wurfl_cloud.egg-info/dependency_links.txt
wurfl_cloud.egg-info/top_level.txt
wurfl_cloud/cache/__init__.py
wurfl_cloud/cache/file_cache.py
wurfl_cloud/cache/interface.py
wurfl_cloud/cache/memcache_cache.py
wurfl_cloud/cache/null_cache.py