Metadata-Version: 1.1
Name: wurfl-cloud
Version: 1.1.1
Summary: UNKNOWN
Home-page: UNKNOWN
Author: ScientiaMobile
Author-email: support@scientiamobile.com
License: 
